sftps-0.1.0.dist-info/METADATA
sftps-0.1.0.dist-info/WHEEL
sftps/__init__.py
sftps/__init__.pyi
sftps/py.typed
sftps/sftps.cpython-314-x86_64-linux-gnu.so
sftps-0.1.0.dist-info/RECORD
